MANIFEST.in
README.rst
bootstrap.py
buildout.cfg
output.html
plone.cfg
setup.cfg
setup.py
collective/__init__.py
collective.carouselbehaviour.egg-info/PKG-INFO
collective.carouselbehaviour.egg-info/SOURCES.txt
collective.carouselbehaviour.egg-info/dependency_links.txt
collective.carouselbehaviour.egg-info/entry_points.txt
collective.carouselbehaviour.egg-info/namespace_packages.txt
collective.carouselbehaviour.egg-info/not-zip-safe
collective.carouselbehaviour.egg-info/paster_plugins.txt
collective.carouselbehaviour.egg-info/requires.txt
collective.carouselbehaviour.egg-info/top_level.txt
collective/carouselbehaviour/INTEGRATION.txt
collective/carouselbehaviour/__init__.py
collective/carouselbehaviour/collectivecarouselbehaviour.py
collective/carouselbehaviour/configure.zcml
collective/carouselbehaviour/tests.py
collective/carouselbehaviour/viewlets.py
collective/carouselbehaviour/locales/README.txt
collective/carouselbehaviour/profiles/default/metadata.xml
collective/carouselbehaviour/profiles/default/types.xml
collective/carouselbehaviour/resources/README.txt
docs/HISTORY.txt
docs/INSTALL.txt
docs/LICENSE.GPL
docs/LICENSE.txt