Metadata-Version: 1.0
Name: collective.carouselbehaviour
Version: 0.1
Summary: Collective carousel behaviour
Home-page: https://github.com/collective/collective.carouselbehaviour
Author: Bogdan Girman
Author-email: bogdan.girman@gmail.com
License: GPL
Keywords: collective carousel behaviour
Platform: UNKNOWN
Classifier: Framework :: Plone :: 4.3
Classifier: Programming Language :: Python
Classifier: Topic :: Software Development :: Libraries :: Python Modules
